{
  "date": "2026-05-18",
  "entries": [
    {
      "timestamp": "2026-05-18T16:31:13",
      "text": "Oliver had a good day with a solid newsletter draft without feeling pressured. He picked up Rowan from school, and they took a leisurely walk home. Rowan shared a story about a classmate who collects rocks, which made the day feel more present and connected.",
      "tags": [
        "newsletter",
        "family",
        "presence"
      ]
    },
    {
      "timestamp": "2026-05-18T16:40:11",
      "text": "Had a productive day without forcing it. Completed a solid draft for the newsletter. Rowan and I enjoyed a walk home from school. He shared a story about a classmate who collects rocks. Felt genuinely present today.",
      "tags": [
        "reflection",
        "family",
        "writing"
      ]
    },
    {
      "timestamp": "2026-05-18T16:47:18",
      "text": "Today's morning pages brought up an insightful concern about the Aliveness book. You've realized that trying to frame 'unclenching' as a system feels forced and contradicts the very argument the book is supposed to make. You spent some time sitting with that thought.",
      "tags": [
        "writing",
        "morning pages",
        "insight"
      ]
    }
  ]
}